#include "../instruction_id.hpp"
#include "identifiers.hpp"

#include "shared/types.hpp"

using namespace internal;


id::jazelle identifiers::jazelle(const u8 opcode) {
    switch (opcode) {
        case 0x00: return id::jazelle::NOP; 
        case 0x01: return id::jazelle::ACONST_NULL; 
        case 0x02: return id::jazelle::ICONST_M1; 
        case 0x03: return id::jazelle::ICONST_0; 
        case 0x04: return id::jazelle::ICONST_1; 
        case 0x05: return id::jazelle::ICONST_2; 
        case 0x06: return id::jazelle::ICONST_3; 
        case 0x07: return id::jazelle::ICONST_4; 
        case 0x08: return id::jazelle::ICONST_5; 
        case 0x09: return id::jazelle::LCONST_0; 
        case 0x0a: return id::jazelle::LCONST_1;
        case 0x0b: return id::jazelle::FCONST_0; 
        case 0x0c: return id::jazelle::FCONST_1; 
        case 0x0d: return id::jazelle::FCONST_2; 
        case 0x0e: return id::jazelle::DCONST_0; 
        case 0x0f: return id::jazelle::DCONST_1; 
        case 0x10: return id::jazelle::BIPUSH; 
        case 0x11: return id::jazelle::SIPUSH; 
        case 0x12: return id::jazelle::LDC; 
        case 0x13: return id::jazelle::LDC_W; 
        case 0x14: return id::jazelle::LDC2_W; 
        case 0x15: return id::jazelle::ILOAD; 
        case 0x16: return id::jazelle::LLOAD; 
        case 0x17: return id::jazelle::FLOAD; 
        case 0x18: return id::jazelle::DLOAD; 
        case 0x19: return id::jazelle::ALOAD; 
        case 0x1a: return id::jazelle::ILOAD_0; 
        case 0x1b: return id::jazelle::ILOAD_1; 
        case 0x1c: return id::jazelle::ILOAD_2; 
        case 0x1d: return id::jazelle::ILOAD_3; 
        case 0x1e: return id::jazelle::LLOAD_0; 
        case 0x1f: return id::jazelle::LLOAD_1; 
        case 0x20: return id::jazelle::LLOAD_2; 
        case 0x21: return id::jazelle::LLOAD_3; 
        case 0x22: return id::jazelle::FLOAD_0; 
        case 0x23: return id::jazelle::FLOAD_1; 
        case 0x24: return id::jazelle::FLOAD_2; 
        case 0x25: return id::jazelle::FLOAD_3; 
        case 0x26: return id::jazelle::DLOAD_0; 
        case 0x27: return id::jazelle::DLOAD_1; 
        case 0x28: return id::jazelle::DLOAD_2; 
        case 0x29: return id::jazelle::DLOAD_3; 
        case 0x2a: return id::jazelle::ALOAD_0; 
        case 0x2b: return id::jazelle::ALOAD_1; 
        case 0x2c: return id::jazelle::ALOAD_2; 
        case 0x2d: return id::jazelle::ALOAD_3; 
        case 0x2e: return id::jazelle::IALOAD; 
        case 0x2f: return id::jazelle::LALOAD; 
        case 0x30: return id::jazelle::FALOAD; 
        case 0x31: return id::jazelle::DALOAD; 
        case 0x32: return id::jazelle::AALOAD; 
        case 0x33: return id::jazelle::BALOAD; 
        case 0x34: return id::jazelle::CALOAD; 
        case 0x35: return id::jazelle::SALOAD; 
        case 0x36: return id::jazelle::ISTORE; 
        case 0x37: return id::jazelle::LSTORE; 
        case 0x38: return id::jazelle::FSTORE; 
        case 0x39: return id::jazelle::DSTORE; 
        case 0x3a: return id::jazelle::ASTORE; 
        case 0x3b: return id::jazelle::ISTORE_0; 
        case 0x3c: return id::jazelle::ISTORE_1; 
        case 0x3d: return id::jazelle::ISTORE_2; 
        case 0x3e: return id::jazelle::ISTORE_3; 
        case 0x3f: return id::jazelle::LSTORE_0; 
        case 0x40: return id::jazelle::LSTORE_1; 
        case 0x41: return id::jazelle::LSTORE_2; 
        case 0x42: return id::jazelle::LSTORE_3; 
        case 0x43: return id::jazelle::FSTORE_0; 
        case 0x44: return id::jazelle::FSTORE_1; 
        case 0x45: return id::jazelle::FSTORE_2; 
        case 0x46: return id::jazelle::FSTORE_3; 
        case 0x47: return id::jazelle::DSTORE_0; 
        case 0x48: return id::jazelle::DSTORE_1; 
        case 0x49: return id::jazelle::DSTORE_2; 
        case 0x4a: return id::jazelle::DSTORE_3; 
        case 0x4b: return id::jazelle::ASTORE_0; 
        case 0x4c: return id::jazelle::ASTORE_1; 
        case 0x4d: return id::jazelle::ASTORE_2; 
        case 0x4e: return id::jazelle::ASTORE_3; 
        case 0x4f: return id::jazelle::IASTORE; 
        case 0x50: return id::jazelle::LASTORE; 
        case 0x51: return id::jazelle::FASTORE; 
        case 0x52: return id::jazelle::DASTORE; 
        case 0x53: return id::jazelle::AASTORE; 
        case 0x54: return id::jazelle::BASTORE; 
        case 0x55: return id::jazelle::CASTORE; 
        case 0x56: return id::jazelle::SASTORE; 
        case 0x57: return id::jazelle::POP; 
        case 0x58: return id::jazelle::POP2; 
        case 0x59: return id::jazelle::DUP; 
        case 0x5a: return id::jazelle::DUP_X1; 
        case 0x5b: return id::jazelle::DUP_X2; 
        case 0x5c: return id::jazelle::DUP2; 
        case 0x5d: return id::jazelle::DUP2_X1; 
        case 0x5e: return id::jazelle::DUP2_X2; 
        case 0x5f: return id::jazelle::SWAP; 
        case 0x60: return id::jazelle::IADD; 
        case 0x61: return id::jazelle::LADD; 
        case 0x62: return id::jazelle::FADD; 
        case 0x63: return id::jazelle::DADD; 
        case 0x64: return id::jazelle::ISUB; 
        case 0x65: return id::jazelle::LSUB; 
        case 0x66: return id::jazelle::FSUB; 
        case 0x67: return id::jazelle::DSUB; 
        case 0x68: return id::jazelle::IMUL; 
        case 0x69: return id::jazelle::LMUL; 
        case 0x6a: return id::jazelle::FMUL; 
        case 0x6b: return id::jazelle::DMUL; 
        case 0x6c: return id::jazelle::IDIV; 
        case 0x6d: return id::jazelle::LDIV; 
        case 0x6e: return id::jazelle::FDIV; 
        case 0x6f: return id::jazelle::DDIV; 
        case 0x70: return id::jazelle::IREM; 
        case 0x71: return id::jazelle::LREM; 
        case 0x72: return id::jazelle::FREM; 
        case 0x73: return id::jazelle::DREM; 
        case 0x74: return id::jazelle::INEG; 
        case 0x75: return id::jazelle::LNEG; 
        case 0x76: return id::jazelle::FNEG; 
        case 0x77: return id::jazelle::DNEG; 
        case 0x78: return id::jazelle::ISHL; 
        case 0x79: return id::jazelle::LSHL; 
        case 0x7a: return id::jazelle::ISHR; 
        case 0x7b: return id::jazelle::LSHR; 
        case 0x7c: return id::jazelle::IUSHR; 
        case 0x7d: return id::jazelle::LUSHR; 
        case 0x7e: return id::jazelle::IAND; 
        case 0x7f: return id::jazelle::LAND; 
        case 0x80: return id::jazelle::IOR; 
        case 0x81: return id::jazelle::LOR; 
        case 0x82: return id::jazelle::IXOR; 
        case 0x83: return id::jazelle::LXOR; 
        case 0x84: return id::jazelle::IINC; 
        case 0x85: return id::jazelle::I2L; 
        case 0x86: return id::jazelle::I2F; 
        case 0x87: return id::jazelle::I2D; 
        case 0x88: return id::jazelle::L2I; 
        case 0x89: return id::jazelle::L2F; 
        case 0x8a: return id::jazelle::L2D; 
        case 0x8b: return id::jazelle::F2I; 
        case 0x8c: return id::jazelle::F2L; 
        case 0x8d: return id::jazelle::F2D; 
        case 0x8e: return id::jazelle::D2I; 
        case 0x8f: return id::jazelle::D2L; 
        case 0x90: return id::jazelle::D2F; 
        case 0x91: return id::jazelle::I2B; 
        case 0x92: return id::jazelle::I2C; 
        case 0x93: return id::jazelle::I2S; 
        case 0x94: return id::jazelle::LCMP; 
        case 0x95: return id::jazelle::FCMPL; 
        case 0x96: return id::jazelle::FCMPG; 
        case 0x97: return id::jazelle::DCMPL; 
        case 0x98: return id::jazelle::DCMPG; 
        case 0x99: return id::jazelle::IFEQ; 
        case 0x9a: return id::jazelle::IFNE; 
        case 0x9b: return id::jazelle::IFLT; 
        case 0x9c: return id::jazelle::IFGE; 
        case 0x9d: return id::jazelle::IFGT; 
        case 0x9e: return id::jazelle::IFLE; 
        case 0x9f: return id::jazelle::IF_ICMPEQ; 
        case 0xa0: return id::jazelle::IF_ICMPNE; 
        case 0xa1: return id::jazelle::IF_ICMPLT; 
        case 0xa2: return id::jazelle::IF_ICMPGE; 
        case 0xa3: return id::jazelle::IF_ICMPGT; 
        case 0xa4: return id::jazelle::IF_ICMPLE; 
        case 0xa5: return id::jazelle::IF_ACMPEQ; 
        case 0xa6: return id::jazelle::IF_ACMPNE; 
        case 0xa7: return id::jazelle::GOTO; 
        case 0xa8: return id::jazelle::JSR; 
        case 0xa9: return id::jazelle::RET; 
        case 0xaa: return id::jazelle::TABLESWITCH; 
        case 0xab: return id::jazelle::LOOKUPSWITCH; 
        case 0xac: return id::jazelle::IRETURN; 
        case 0xad: return id::jazelle::LRETURN; 
        case 0xae: return id::jazelle::FRETURN; 
        case 0xaf: return id::jazelle::DRETURN; 
        case 0xb0: return id::jazelle::ARETURN; 
        case 0xb1: return id::jazelle::RETURN; 
        case 0xb2: return id::jazelle::GETSTATIC; 
        case 0xb3: return id::jazelle::PUTSTATIC; 
        case 0xb4: return id::jazelle::GETFIELD; 
        case 0xb5: return id::jazelle::PUTFIELD; 
        case 0xb6: return id::jazelle::INVOKEVIRTUAL; 
        case 0xb7: return id::jazelle::INVOKESPECIAL; 
        case 0xb8: return id::jazelle::INVOKESTATIC; 
        case 0xb9: return id::jazelle::INVOKEINTERFACE; 
        case 0xba: return id::jazelle::INVOKEDYNAMIC; 
        case 0xbb: return id::jazelle::NEW; 
        case 0xbc: return id::jazelle::NEWARRAY; 
        case 0xbd: return id::jazelle::ANEWARRAY; 
        case 0xbe: return id::jazelle::ARRAYLENGTH; 
        case 0xbf: return id::jazelle::ATHROW; 
        case 0xc0: return id::jazelle::CHECKCAST; 
        case 0xc1: return id::jazelle::INSTANCEOF; 
        case 0xc2: return id::jazelle::MONITORENTER; 
        case 0xc3: return id::jazelle::MONITOREXIT; 
        case 0xc4: return id::jazelle::WIDE; 
        case 0xc5: return id::jazelle::MULTIANEWARRAY; 
        case 0xc6: return id::jazelle::IFNULL; 
        case 0xc7: return id::jazelle::IFNONNULL; 
        case 0xc8: return id::jazelle::GOTO_W; 
        case 0xc9: return id::jazelle::JSR_W; 
        case 0xca: return id::jazelle::BREAKPOINT; 
        case 0xfe: return id::jazelle::IMPDEP1; 
        case 0xff: return id::jazelle::IMPDEP2; 
        default: shared::out::error("TODO"); // unknown instruction, idk if there's like a specific exception handler for this
    }
}
